celery_director-0.10.0.dist-info/licenses/AUTHORS
celery_director-0.10.0.dist-info/licenses/LICENSE
director/VERSION
director/__init__.py
director/_auto.py
director/auth.py
director/builder.py
director/cli.py
director/context.py
director/exceptions.py
director/extensions.py
director/settings.py
director/utils.py
director/api/__init__.py
director/api/workflows.py
director/commands/__init__.py
director/commands/assets.py
director/commands/celery.py
director/commands/db.py
director/commands/init.py
director/commands/user.py
director/commands/webserver.py
director/commands/workflows.py
director/migrations/README
director/migrations/alembic.ini
director/migrations/env.py
director/migrations/script.py.mako
director/migrations/versions/05cf96d6fcae_add_task_result.py
director/migrations/versions/063ff371f2da_add_index_on_workflow_id_in_task_table.py
director/migrations/versions/2ac615d6850b_force_varchar_255.py
director/migrations/versions/30d6f6636351_initial_migration.py
director/migrations/versions/3f8466b16023_add_users_table.py
director/migrations/versions/46e4acde004e_add_cascade_in_task_model.py
director/migrations/versions/9817ccf13cb5_add_is_hook_on_task.py
director/migrations/versions/9d563aaa548b_add_workflow_comment.py
director/models/__init__.py
director/models/tasks.py
director/models/users.py
director/models/utils.py
director/models/workflows.py
director/static/script.js
director/static/style.css
director/tasks/__init__.py
director/tasks/base.py
director/tasks/periodic.py
director/tasks/workflows.py
director/templates/error.html
director/templates/index.html
director/views/__init__.py
tests/__init__.py
tests/conftest.py
tests/test_api.py
tests/test_auth.py
tests/test_builder.py
tests/test_sentry.py
tests/test_users.py
tests/test_views.py
tests/test_workflows.py
celery_director-0.10.0.dist-info/METADATA
celery_director-0.10.0.dist-info/WHEEL
celery_director-0.10.0.dist-info/entry_points.txt
celery_director-0.10.0.dist-info/top_level.txt
celery_director-0.10.0.dist-info/RECORD
