Metadata-Version: 2.4
Name: celery-director
Version: 0.10.0
Summary: Celery Director
Home-page: https://github.com/ovh/celery-director
Author: OVHcloud
Author-email: opensource@ovhcloud.com
License: BSD
Classifier: Development Status :: 4 - Beta
Classifier: Environment :: Console
Classifier: Environment :: Web Environment
Classifier: Intended Audience :: Developers
Classifier: License :: OSI Approved :: BSD License
Classifier: Programming Language :: Python :: 3
Classifier: Programming Language :: Python :: 3.9
Classifier: Programming Language :: Python :: 3.10
Classifier: Programming Language :: Python :: 3.11
Classifier: Topic :: System :: Monitoring
Requires-Python: ~=3.9
License-File: LICENSE
License-File: AUTHORS
Requires-Dist: celery==5.5.1
Requires-Dist: flower==1.2.0
Requires-Dist: kombu==5.5.2
Requires-Dist: psycopg2-binary==2.9.5
Requires-Dist: SQLAlchemy==1.4.44
Requires-Dist: sqlalchemy-utils==0.38.3
Requires-Dist: mysql-connector-python==8.0.31
Requires-Dist: redis==4.4.4
Requires-Dist: alembic==1.8.1
Requires-Dist: Flask==2.3.2
Requires-Dist: Flask-SQLAlchemy==2.5.1
Requires-Dist: Flask-json-schema==0.0.5
Requires-Dist: Flask-Migrate==3.1.0
Requires-Dist: Flask-HTTPAuth==4.5.0
Requires-Dist: Werkzeug==2.3.3
Requires-Dist: gunicorn==20.0.4
Requires-Dist: environs==14.1.1
Requires-Dist: pyyaml==6.0.1
Requires-Dist: terminaltables==3.1.0
Requires-Dist: pluginbase==1.0.0
Requires-Dist: sentry-sdk==1.14.0
Requires-Dist: importlib-metadata==4.13.0
Requires-Dist: urllib3==1.26.15
Provides-Extra: dev
Requires-Dist: tox==3.5.3; extra == "dev"
Requires-Dist: black==22.3.0; extra == "dev"
Provides-Extra: ci
Requires-Dist: pytest; extra == "ci"
Requires-Dist: pytest-cov; extra == "ci"
Provides-Extra: doc
Requires-Dist: mkdocs==1.3.0; extra == "doc"
Requires-Dist: mkdocs-material==8.2.9; extra == "doc"
Dynamic: author
Dynamic: author-email
Dynamic: classifier
Dynamic: description
Dynamic: description-content-type
Dynamic: home-page
Dynamic: license
Dynamic: license-file
Dynamic: provides-extra
Dynamic: requires-dist
Dynamic: requires-python
Dynamic: summary
